DataBlock.py
PLC.py
README.md
Utility.py
setup.cfg
setup.py
DataTypes/DTUint.py
DataTypes/DTbool.py
DataTypes/DTdint.py
DataTypes/DTint.py
DataTypes/DTstring.py
DataTypes/DTtime.py
DataTypes/__init__.py
EasyS7_2.egg-info/PKG-INFO
EasyS7_2.egg-info/SOURCES.txt
EasyS7_2.egg-info/dependency_links.txt
EasyS7_2.egg-info/top_level.txt